{"type":"Topology","objects":{"cities_caf":{"type":"GeometryCollection","geometries":[{"type":"Point","coordinates":[165,0]},{"type":"Point","coordinates":[5856,5489]},{"type":"Point","coordinates":[0,4087]},{"type":"Point","coordinates":[4648,3635]},{"type":"Point","coordinates":[4635,9999]},{"type":"Point","coordinates":[9999,2765]},{"type":"Point","coordinates":[2714,281]}]}},"arcs":[],"transform":{"scale":[0.001090114830172264,0.0004159593612372805],"translate":[15.599967405874338,4.249958922233873]}}