{"type":"Topology","objects":{"states_nir":{"type":"GeometryCollection","geometries":[{"type":"Polygon","properties":{"name":"Belfast"},"id":"GBR-2082","arcs":[[0,1,2,3,4,5]]},{"type":"Polygon","properties":{"name":"Derry"},"id":"GBR-2083","arcs":[[6,7,8]]},{"type":"Polygon","properties":{"name":"Omagh"},"id":"GBR-2084","arcs":[[9,10,11,12,13]]},{"type":"Polygon","properties":{"name":"Armagh"},"id":"GBR-2085","arcs":[[14,15,16,17,18]]},{"type":"Polygon","properties":{"name":"Newry and Mourne"},"id":"GBR-2086","arcs":[[19,20,-17,21]]},{"type":"Polygon","properties":{"name":"Banbridge"},"id":"GBR-2087","arcs":[[22,-22,-16,23,24]]},{"type":"Polygon","properties":{"name":"Craigavon"},"id":"GBR-2088","arcs":[[25,-24,-15,26,27,28]]},{"type":"Polygon","properties":{"name":"Dungannon"},"id":"GBR-2089","arcs":[[-27,-19,29,30,-12,31]]},{"type":"Polygon","properties":{"name":"Lisburn"},"id":"GBR-2090","arcs":[[32,33,-25,-26,34,-4]]},{"type":"Polygon","properties":{"name":"Cookstown"},"id":"GBR-2091","arcs":[[35,-28,-32,-11,36]]},{"type":"Polygon","properties":{"name":"Antrim"},"id":"GBR-2092","arcs":[[37,-5,-35,-29,-36,38,39]]},{"type":"Polygon","properties":{"name":"Magherafelt"},"id":"GBR-2093","arcs":[[40,-39,-37,-10,41,42,43,44]]},{"type":"Polygon","properties":{"name":"Ballymena"},"id":"GBR-2094","arcs":[[45,46,-40,-41,47,48]]},{"type":"Polygon","properties":{"name":"Larne"},"id":"GBR-2095","arcs":[[49,50,-46,51,52]]},{"type":"Polygon","properties":{"name":"Carrickfergus"},"id":"GBR-2096","arcs":[[53,54,-50]]},{"type":"Polygon","properties":{"name":"Newtownabbey"},"id":"GBR-2097","arcs":[[-55,55,-6,-38,-47,-51]]},{"type":"Polygon","properties":{"name":"North Down"},"id":"GBR-2098","arcs":[[56,57,-2,58]]},{"type":"Polygon","properties":{"name":"Down"},"id":"GBR-2099","arcs":[[59,-20,-23,-34,60,61]]},{"type":"Polygon","properties":{"name":"Coleraine"},"id":"GBR-2100","arcs":[[62,-44,63,64,65]]},{"type":"Polygon","properties":{"name":"Ballymoney"},"id":"GBR-2101","arcs":[[-48,-45,-63,66]]},{"type":"Polygon","properties":{"name":"Limavady"},"id":"GBR-2102","arcs":[[-64,-43,67,-7,68]]},{"type":"Polygon","properties":{"name":"Castlereagh"},"id":"GBR-2103","arcs":[[69,-61,-33,-3,-58]]},{"type":"Polygon","properties":{"name":"Strabane"},"id":"GBR-2135","arcs":[[-68,-42,-14,70,71,-8]]},{"type":"Polygon","properties":{"name":"Fermanagh"},"id":"GBR-2136","arcs":[[-13,-31,72,-71]]},{"type":"Polygon","properties":{"name":"Ards"},"id":"GBR-2137","arcs":[[-62,-70,-57,73]]},{"type":"Polygon","properties":{"name":"Moyle"},"id":"GBR-2773","arcs":[[-52,-49,-67,-66,74]]}]}},"arcs":[[[8233,5060],[161,-199]],[[8394,4861],[230,-70]],[[8624,4791],[-539,-497]],[[8085,4294],[-409,566]],[[7676,4860],[160,330]],[[7836,5190],[397,-130]],[[3695,8391],[513,-1933]],[[4208,6458],[-1489,1069]],[[2719,7527],[223,800],[753,64]],[[4504,6062],[-147,-216]],[[4357,5846],[30,-1368]],[[4387,4478],[-602,-894],[-878,-320]],[[2907,3264],[-527,-209],[-681,1623]],[[1699,4678],[1792,1260],[1013,124]],[[5881,3539],[549,-576]],[[6430,2963],[166,-970]],[[6596,1993],[-1059,-855]],[[5537,1138],[-645,486],[-169,776]],[[4723,2400],[272,722],[886,417]],[[7752,1742],[658,-518]],[[8410,1224],[-168,-769],[-472,-455],[-897,570],[-1219,-563],[-117,1131]],[[6596,1993],[1156,-251]],[[8101,2845],[-349,-1103]],[[6430,2963],[715,326]],[[7145,3289],[956,-444]],[[6949,4609],[196,-1320]],[[5881,3539],[99,634]],[[5980,4173],[333,240]],[[6313,4413],[636,196]],[[4723,2400],[-658,709],[-515,-628]],[[3550,2481],[-643,783]],[[4387,4478],[1593,-305]],[[8085,4294],[318,-624]],[[8403,3670],[-302,-825]],[[6949,4609],[727,251]],[[6087,5552],[226,-1139]],[[4357,5846],[1730,-294]],[[7609,6263],[227,-1073]],[[6087,5552],[66,635]],[[6153,6187],[1456,76]],[[6057,7292],[96,-1105]],[[4504,6062],[45,399]],[[4549,6461],[501,789]],[[5050,7250],[957,283]],[[6007,7533],[50,-241]],[[7544,7879],[288,-433],[61,-1128]],[[7893,6318],[-284,-55]],[[6057,7292],[1154,930]],[[7211,8222],[333,-343]],[[9049,6085],[-724,-9]],[[8325,6076],[-432,242]],[[7544,7879],[444,570]],[[7988,8449],[1061,-2364]],[[9049,6085],[-682,-731]],[[8367,5354],[-42,722]],[[8367,5354],[-134,-294]],[[9516,5271],[-705,-468]],[[8811,4803],[-187,-12]],[[8394,4861],[450,477],[672,-67]],[[9244,3548],[325,-821],[-228,-911],[-931,-592]],[[8403,3670],[181,103]],[[8584,3773],[660,-225]],[[6026,9224],[-362,-601],[343,-1090]],[[5050,7250],[-211,2192]],[[4839,9442],[1074,412]],[[5913,9854],[113,-630]],[[6026,9224],[1185,-1002]],[[4549,6461],[-341,-3]],[[3695,8391],[488,186],[656,865]],[[8811,4803],[-227,-1030]],[[1699,4678],[-53,33]],[[1646,4711],[-730,469],[1303,774],[500,1573]],[[3550,2481],[160,-693],[-604,-1139],[-1097,209],[-837,534],[-213,740],[-959,1206],[565,865],[423,-94],[658,602]],[[9516,5271],[483,-1708],[-755,-15]],[[5913,9854],[709,145],[925,-251],[441,-1299]]],"transform":{"scale":[0.0002722846129612904,0.00012062973877388289],"translate":[-8.156034911999882,54.036444403000075]}}